{
	"0": {
		"icon": "FaCalculator",
		"title": "Ordinary Account (OA)",
		"slug": "/ordinary_account",
		"description": "Description goes here"
	},
	"1": {
		"icon": "FaCalculator",
		"title": "Special Account (SA)",
		"slug": "/special_account",
		"description": "Description goes here"
	},
	"2": {
		"icon": "FaCalculator",
		"title": "Medisave Account (MA)",
		"slug": "/medisave_account",
		"description": "Description goes here"
	},
	"3": {
		"icon": "FaCalculator",
		"title": "Apply/change GIRO for Repayment of Education Loan",
		"slug": "/giro_education",
		"description": "Description goes here"
	},
	"4": {
		"icon": "FaCalculator",
		"title": "Defer Repayment",
		"slug": "/defer_repayment",
		"description": "Description goes here"
	},
	"5": {
		"icon": "FaCalculator",
		"title": "Change Monthly Instalment",
		"slug": "/monthly_instalment",
		"description": "Description goes here"
	},
	"6": {
		"icon": "FaCalculator",
		"title": "CPFIS Self-Awareness Questionnaire (SAQ) Status",
		"slug": "/saq_status",
		"description": "Description goes here"
	},
	"7": {
		"icon": "FaCalculator",
		"title": "Apply to Withdraw",
		"slug": "/apply_withdraw",
		"description": "Description goes here"
	},
	"8": {
		"icon": "FaCalculator",
		"title": "Apply to Transfer",
		"slug": "/apply_transfer",
		"description": "Description goes here"
	}
}
